answer_college_supplemental/__about__.py
answer_college_supplemental/__init__.py
answer_college_supplemental/main.py
answer_college_supplemental-2.0.0.dist-info/LICENSE.txt
answer_college_supplemental-2.0.0.dist-info/METADATA
answer_college_supplemental-2.0.0.dist-info/WHEEL
answer_college_supplemental-2.0.0.dist-info/entry_points.txt
answer_college_supplemental-2.0.0.dist-info/top_level.txt
answer_college_supplemental-2.0.0.dist-info/RECORD
