Metadata-Version: 2.1
Name: answer-college-supplemental
Version: 2.0.0
Summary: A CLI tool for gaining inspiration for college supplementals. Do NOT submit these generated essays to colleges.
Home-page: UNKNOWN
Author: Vishy Gopal
Author-email: vishy1290@gmail.com
License: UNKNOWN
Platform: UNKNOWN
Requires-Python: >=3.8
License-File: LICENSE.txt
